{
  "version": "1.0",
  "textbook": "人教版",
  "grade": 1,
  "semester": 2,
  "units": [
    {
      "id": "g1s2u1",
      "grade": 1,
      "semester": 2,
      "unit": 1,
      "title": "四季与识字",
      "lessons": ["识字1·春夏秋冬", "识字2·姓氏歌", "识字3·小青蛙", "识字4·猜字谜"],
      "newChars": ["春", "风", "冬", "雪", "花", "青", "清", "晴", "生", "字", "左", "右", "红", "时", "动"],
      "boardRows": 3,
      "boardCols": 4,
      "pairs": [["春", "天"], ["冬", "天"], ["雪", "花"], ["花", "草"], ["青", "草"], ["生", "日"], ["左", "右"], ["红", "花"], ["清", "早"], ["晴", "天"], ["春", "风"], ["冬", "日"], ["花", "朵"], ["花", "生"], ["生", "字"], ["动", "手"], ["红", "日"], ["风", "雨"], ["雪", "人"], ["青", "山"]]
    },
    {
      "id": "g1s2u2",
      "grade": 1,
      "semester": 2,
      "unit": 2,
      "title": "祖国与太阳",
      "lessons": ["课文1·吃水不忘挖井人", "课文2·我多想去看看", "课文3·一个接一个", "课文4·四个太阳"],
      "newChars": ["国", "王", "北", "京", "门", "广", "太", "阳", "校", "金", "秋", "以", "主", "江", "住"],
      "boardRows": 3,
      "boardCols": 4,
      "pairs": [["中", "国"], ["国", "王"], ["北", "京"], ["大", "门"], ["广", "大"], ["太", "阳"], ["学", "校"], ["金", "鱼"], ["秋", "天"], ["以", "后"], ["主", "人"], ["江", "水"], ["居", "住"], ["阳", "光"], ["北", "方"], ["校", "门"], ["金", "子"], ["秋", "风"], ["天", "门"], ["长", "江"]]
    },
    {
      "id": "g1s2u3",
      "grade": 1,
      "semester": 2,
      "unit": 3,
      "title": "伙伴与快乐",
      "lessons": ["课文5·小公鸡和小鸭子", "课文6·树和喜鹊", "课文7·怎么都快乐"],
      "newChars": ["他", "河", "说", "也", "地", "听", "哥", "快", "玩", "很", "音", "讲", "行", "许"],
      "boardRows": 3,
      "boardCols": 4,
      "pairs": [["他", "们"], ["河", "水"], ["说", "话"], ["也", "许"], ["土", "地"], ["听", "见"], ["哥", "哥"], ["快", "乐"], ["好", "玩"], ["很", "多"], ["音", "乐"], ["讲", "课"], ["行", "走"], ["许", "多"], ["听", "说"], ["大", "哥"], ["飞", "快"], ["玩", "水"], ["河", "边"], ["地", "方"]]
    },
    {
      "id": "g1s2u4",
      "grade": 1,
      "semester": 2,
      "unit": 4,
      "title": "夜色与端午",
      "lessons": ["课文8·静夜思", "课文9·夜色", "课文10·端午粽", "课文11·彩虹"],
      "newChars": ["思", "床", "光", "故", "乡", "色", "晚", "笑", "再", "午", "节", "叶", "米", "真", "豆", "高", "兴"],
      "boardRows": 3,
      "boardCols": 4,
      "pairs": [["故", "乡"], ["月", "光"], ["高", "兴"], ["思", "乡"], ["节", "日"], ["树", "叶"], ["大", "米"], ["认", "真"], ["中", "午"], ["再", "见"], ["花", "朵"], ["乡", "音"], ["春", "光"], ["花", "色"], ["节", "气"], ["思", "念"], ["天", "真"], ["红", "豆"], ["晚", "上"], ["大", "笑"]]
    },
    {
      "id": "g1s2u5",
      "grade": 1,
      "semester": 2,
      "unit": 5,
      "title": "动物与操场",
      "lessons": ["识字5·动物儿歌", "识字6·古对今", "识字7·操场上", "识字8·人之初"],
      "newChars": ["间", "迷", "运", "池", "欢", "网", "古", "凉", "语", "香", "打", "跑", "足", "声", "身", "体", "习", "远"],
      "boardRows": 3,
      "boardCols": 4,
      "pairs": [["中", "间"], ["入", "迷"], ["运", "动"], ["水", "池"], ["欢", "笑"], ["上", "网"], ["古", "今"], ["清", "凉"], ["语", "文"], ["香", "气"], ["打", "水"], ["跑", "步"], ["手", "足"], ["声", "音"], ["身", "体"], ["学", "习"], ["远", "方"], ["古", "诗"], ["凉", "风"], ["打", "开"]]
    },
    {
      "id": "g1s2u6",
      "grade": 1,
      "semester": 2,
      "unit": 6,
      "title": "荷叶与雨天",
      "lessons": ["课文12·古诗二首", "课文13·荷叶圆圆", "课文14·要下雨了"],
      "newChars": ["首", "采", "无", "树", "爱", "亮", "机", "台", "放", "鱼", "美", "直", "边", "加"],
      "boardRows": 3,
      "boardCols": 4,
      "pairs": [["首", "先"], ["采", "花"], ["无", "人"], ["树", "木"], ["可", "爱"], ["月", "亮"], ["飞", "机"], ["阳", "台"], ["放", "学"], ["小", "鱼"], ["美", "丽"], ["一", "直"], ["河", "边"], ["加", "上"], ["树", "叶"], ["亮", "光"], ["台", "风"], ["放", "手"], ["鱼", "儿"], ["无", "声"]]
    },
    {
      "id": "g1s2u7",
      "grade": 1,
      "semester": 2,
      "unit": 7,
      "title": "文具与时间",
      "lessons": ["课文15·文具的家", "课文16·一分钟", "课文17·动物王国开大会", "课文18·小猴子下山"],
      "newChars": ["文", "次", "找", "丢", "写", "本", "放", "忘", "包", "桌", "椅", "迟", "到", "闹", "钟", "决", "定"],
      "boardRows": 3,
      "boardCols": 4,
      "pairs": [["语", "文"], ["下", "次"], ["找", "到"], ["丢", "失"], ["写", "字"], ["本", "子"], ["放", "下"], ["忘", "记"], ["书", "包"], ["桌", "子"], ["椅", "子"], ["迟", "到"], ["来", "到"], ["闹", "钟"], ["决", "定"], ["开", "会"], ["文", "具"], ["包", "子"], ["定", "时"], ["写", "作"]]
    },
    {
      "id": "g1s2u8",
      "grade": 1,
      "semester": 2,
      "unit": 8,
      "title": "童话与动物",
      "lessons": ["课文19·棉花姑娘", "课文20·咕咚", "课文21·小壁虎借尾巴"],
      "newChars": ["病", "医", "治", "用", "雪", "棉", "花", "请", "帮", "呢", "它", "跑", "告", "诉", "把", "借"],
      "boardRows": 3,
      "boardCols": 4,
      "pairs": [["生", "病"], ["医", "生"], ["治", "病"], ["有", "用"], ["雪", "花"], ["棉", "花"], ["请", "问"], ["帮", "忙"], ["它", "们"], ["跑", "步"], ["告", "诉"], ["一", "把"], ["借", "书"], ["花", "朵"], ["用", "心"], ["请", "客"], ["帮", "手"], ["快", "跑"], ["看", "病"], ["借", "用"]]
    }
  ]
}
